{
  "attribution" : "these values were partially taken from https://en.wikipedia.org/wiki/Commonly_misspelled_English_words, content was modified to make it suitable in text matching software and some values have been removed and/or renamed",
  "license": "This file is released under Creative Commons Attribution-ShareAlike license:  http://creativecommons.org/licenses/by-sa/3.0/",
  "singleWordSynonyms":[
    {
      "words":["absence"],
      "synonyms":[
        {"fitRating":1, "values":["absence", "absense"]},
        {"fitRating":0.95, "values":["absance"]}
      ]
    },
    {
      "words":["acceptable"],
      "synonyms":[
        {"fitRating":1, "values":["acceptable", "acceptible"]}
      ]
    },
    {
      "words":["accidentally", "accidently"],
      "synonyms":[
        {"fitRating":1, "values":["accidentally", "accidently", "accidentaly"]}
      ]
    },
    {
      "words":["accommodate"],
      "synonyms":[
        {"fitRating":1, "values":["accommodate", "accomodate", "acommodate", "acomodate"]}
      ]
    },
    {
      "words":["achieve"],
      "synonyms":[
        {"fitRating":1, "values":["achieve"]},
        {"fitRating":0.95, "values":["acheive"]}
      ]
    },
    {
      "words":["acknowledge"],
      "synonyms":[
        {"fitRating":1, "values":["acknowledge", "acknowlege", "aknowledge"]}
      ]
    },
    {
      "words":["acquaintance"],
      "synonyms":[
        {"fitRating":1, "values":["acquaintance", "acquaintence", "aquaintance"]}
      ]
    },
    {
      "words":["acquire"],
      "synonyms":[
        {"fitRating":1, "values":["acquire", "aquire", "adquire"]}
      ]
    },
    {
      "words":["acquit"],
      "synonyms":[
        {"fitRating":1, "values":["acquit", "aquit"]}
      ]
    },
    {
      "words":["acreage"],
      "synonyms":[
        {"fitRating":1, "values":["acreage", "acrage", "acerage"]}
      ]
    },
    {
      "words":["address"],
      "synonyms":[
        {"fitRating":1, "values":["address", "adress"]}
      ]
    },
    {
      "words":["adultery"],
      "synonyms":[
        {"fitRating":1, "values":["adultery", "adultary"]}
      ]
    }


  ]
}